{"nodes": [{"id": "phase_1_foundation", "label": "Phase 1 \u2014 Foundation", "file_type": "document", "source_file": "docs/phases/PHASE-1-foundation.md", "source_location": null, "source_url": null, "captured_at": null, "author": null, "contributor": null}, {"id": "health_endpoint", "label": "Health Endpoint (GET /health)", "file_type": "document", "source_file": "docs/phases/PHASE-1-foundation.md", "source_location": null, "source_url": null, "captured_at": null, "author": null, "contributor": null}, {"id": "db_pool", "label": "PostgreSQL Connection Pool", "file_type": "document", "source_file": "docs/phases/PHASE-1-foundation.md", "source_location": null, "source_url": null, "captured_at": null, "author": null, "contributor": null}, {"id": "migrations_001", "label": "Migration 001 \u2014 Initial", "file_type": "document", "source_file": "docs/phases/PHASE-1-foundation.md", "source_location": null, "source_url": null, "captured_at": null, "author": null, "contributor": null}, {"id": "config_module", "label": "Config Module", "file_type": "document", "source_file": "docs/phases/PHASE-1-foundation.md", "source_location": null, "source_url": null, "captured_at": null, "author": null, "contributor": null}, {"id": "error_module", "label": "Error Module (EngineError)", "file_type": "document", "source_file": "docs/phases/PHASE-1-foundation.md", "source_location": null, "source_url": null, "captured_at": null, "author": null, "contributor": null}, {"id": "tracing_logging", "label": "Structured Logging (tracing)", "file_type": "document", "source_file": "docs/phases/PHASE-1-foundation.md", "source_location": null, "source_url": null, "captured_at": null, "author": null, "contributor": null}, {"id": "docker_compose_setup", "label": "Docker Compose PostgreSQL Setup", "file_type": "document", "source_file": "docs/phases/PHASE-1-foundation.md", "source_location": null, "source_url": null, "captured_at": null, "author": null, "contributor": null}], "edges": [{"source": "phase_1_foundation", "target": "phase_0_evaluation", "relation": "references", "confidence": "EXTRACTED", "confidence_score": 1.0, "source_file": "docs/phases/PHASE-1-foundation.md", "source_location": null, "weight": 1.0}, {"source": "phase_1_foundation", "target": "config_module", "relation": "implements", "confidence": "EXTRACTED", "confidence_score": 1.0, "source_file": "docs/phases/PHASE-1-foundation.md", "source_location": null, "weight": 1.0}, {"source": "phase_1_foundation", "target": "error_module", "relation": "implements", "confidence": "EXTRACTED", "confidence_score": 1.0, "source_file": "docs/phases/PHASE-1-foundation.md", "source_location": null, "weight": 1.0}, {"source": "phase_1_foundation", "target": "db_pool", "relation": "implements", "confidence": "EXTRACTED", "confidence_score": 1.0, "source_file": "docs/phases/PHASE-1-foundation.md", "source_location": null, "weight": 1.0}, {"source": "phase_1_foundation", "target": "health_endpoint", "relation": "implements", "confidence": "EXTRACTED", "confidence_score": 1.0, "source_file": "docs/phases/PHASE-1-foundation.md", "source_location": null, "weight": 1.0}, {"source": "phase_1_foundation", "target": "migrations_001", "relation": "implements", "confidence": "EXTRACTED", "confidence_score": 1.0, "source_file": "docs/phases/PHASE-1-foundation.md", "source_location": null, "weight": 1.0}, {"source": "phase_1_foundation", "target": "tracing_logging", "relation": "implements", "confidence": "EXTRACTED", "confidence_score": 1.0, "source_file": "docs/phases/PHASE-1-foundation.md", "source_location": null, "weight": 1.0}, {"source": "phase_1_foundation", "target": "docker_compose_setup", "relation": "implements", "confidence": "EXTRACTED", "confidence_score": 1.0, "source_file": "docs/phases/PHASE-1-foundation.md", "source_location": null, "weight": 1.0}, {"source": "phase_1_foundation", "target": "tokio_runtime", "relation": "implements", "confidence": "INFERRED", "confidence_score": 0.9, "source_file": "docs/phases/PHASE-1-foundation.md", "source_location": null, "weight": 1.0}, {"source": "phase_1_foundation", "target": "axum_web_framework", "relation": "implements", "confidence": "INFERRED", "confidence_score": 0.9, "source_file": "docs/phases/PHASE-1-foundation.md", "source_location": null, "weight": 1.0}, {"source": "phase_1_foundation", "target": "sqlx_database_driver", "relation": "implements", "confidence": "INFERRED", "confidence_score": 0.9, "source_file": "docs/phases/PHASE-1-foundation.md", "source_location": null, "weight": 1.0}], "hyperedges": []}